setup.py
py_chunkit/__init__.py
py_chunkit.egg-info/PKG-INFO
py_chunkit.egg-info/SOURCES.txt
py_chunkit.egg-info/dependency_links.txt
py_chunkit.egg-info/top_level.txt