Metadata-Version: 1.0
Name: py-chunkit
Version: 0.2
Summary: A WSGI chunked request parse midware
Home-page: http://xiangyang.li/project/py_chunkit
Author: bac
Author-email: wo@xiangyang.li
License: Apache License
Keywords: WSGI,Chunked,Flask,uWSGI,Transfer-Encoding
Platform: any
